README.md
setup.py
tavisod/__init__.py
tavisod/tavisod.py
tavisod.egg-info/PKG-INFO
tavisod.egg-info/SOURCES.txt
tavisod.egg-info/dependency_links.txt
tavisod.egg-info/requires.txt
tavisod.egg-info/top_level.txt