Metadata-Version: 1.0
Name: tavisod
Version: 1.0.5
Summary: google cloud secret manager fetcher for micro services
Home-page: UNKNOWN
Author: Mike
Author-email: mikej@antidotehealth.com
License: UNKNOWN
Platform: UNKNOWN
